uncontrol/__init__.py
uncontrol/admin.py
uncontrol/apps.py
uncontrol/exceptions.py
uncontrol/forms.py
uncontrol/gpg.py
uncontrol/models.py
uncontrol/tests.py
uncontrol/urls.py
uncontrol/views.py
uncontrol/migrations/__init__.py
uncontrol/templates/base.html
uncontrol/templates/registration/login.html
uncontrol/templates/uncontrol/dashboard.html
uncontrol/templates/uncontrol/form_with_result.html
uncontrol-0.3.6.dist-info/licenses/LICENSE
uncontrol-0.3.6.dist-info/METADATA
uncontrol-0.3.6.dist-info/WHEEL
uncontrol-0.3.6.dist-info/top_level.txt
uncontrol-0.3.6.dist-info/RECORD
