Metadata-Version: 2.4
Name: uncontrol
Version: 0.3.6
Summary: Add your description here
Author-email: Frank Hennige <frank@hennige-it.de>
License-Expression: AGPL-3.0-or-later
Project-URL: Homepage, https://github.com/FrankHennige/uncontrol
Project-URL: Issues, https://github.com/FrankHennige/uncontrol/issues
Classifier: Programming Language :: Python :: 3
Classifier: Operating System :: OS Independent
Requires-Python: >=3.9
License-File: LICENSE
Requires-Dist: cryptography>=46.0.2
Requires-Dist: django-bootstrap5>=25.2
Requires-Dist: django-htmx>=1.26.0
Requires-Dist: htmx-components>=0.1.9
Requires-Dist: python-gnupg>=0.5.5
Provides-Extra: build
Requires-Dist: uv~=0.8.24; extra == "build"
Dynamic: license-file
